{
  "catalog_info": {
    "title": "District-wise Livestock Census - Madhya Pradesh (2021)",
    "description": "This dataset provides the count of major livestock species (cattle, buffalo, goat, and sheep) at the district level in Madhya Pradesh for the year 2021. It is valuable for AI/ML applications focused on livestock population estimation, resource allocation, and agricultural planning. The data can also be used for predictive modeling of livestock dynamics.",
    "sector": "Livestock",
    "keywords": [
      "livestock",
      "census",
      "cattle",
      "buffalo",
      "goat",
      "sheep",
      "population",
      "Madhya Pradesh",
      "agriculture"
    ],
    "language": "English",
    "update_frequency": "Annual"
  },
  "provenance": {
    "source": "Ministry of Fisheries, Animal Husbandry & Dairying",
    "publisher": "Department of Animal Husbandry, Government of Madhya Pradesh",
    "jurisdiction": "Madhya Pradesh",
    "data_owner": "Government of India",
    "contact": "Not available"
  },
  "spatial_temporal": {
    "temporal_coverage": "2021",
    "spatial_coverage": "Madhya Pradesh State",
    "granularity": "District"
  },
  "usage": {
    "license": "Open Government Data License - India",
    "access_constraints": "None - Public Data",
    "use_cases": [
      "AI/ML training",
      "Policy analysis",
      "Research",
      "Livestock management",
      "Predictive modeling"
    ],
    "target_audience": [
      "Researchers",
      "Data Scientists",
      "Policy Makers",
      "Agricultural Experts",
      "Startups"
    ]
  },
  "technical_metadata": {
    "format": "CSV",
    "original_filename": "mp_livestock_census.csv",
    "row_count": 5,
    "column_count": 8,
    "columns": [
      "district",
      "state",
      "cattle_count",
      "buffalo_count",
      "goat_count",
      "sheep_count",
      "year",
      "survey_officer"
    ],
    "data_quality": {
      "completeness": 1.0,
      "standardized": true,
      "ai_ready": true
    },
    "transformations_applied": {
      "District": "district",
      "State": "state",
      "Cattle": "cattle_count",
      "Buffalo": "buffalo_count",
      "Goat": "goat_count",
      "Sheep": "sheep_count",
      "Year": "year",
      "Survey_Officer": "survey_officer"
    }
  }
}